YvesCMD/__init__.py
YvesCMD/src/__init__.py
YvesCMD/src/register.py
YvesCMD/src/yvescmd.py
YvesCMD/src/extensions/__init__.py
YvesCMD/src/extensions/anwser.py
YvesCMD/src/extensions/select.py
YvesCMD/src/extensions/state.py
YvesCMD/src/utils/__init__.py
YvesCMD/src/utils/detector.py
YvesCMD/src/utils/hooks.py
YvesCMD/src/utils/register.py
yvesCMD-0.0.6.dist-info/METADATA
yvesCMD-0.0.6.dist-info/WHEEL
yvesCMD-0.0.6.dist-info/top_level.txt
yvesCMD-0.0.6.dist-info/RECORD
