Metadata-Version: 2.1
Name: yvesCMD
Version: 0.0.6
Home-page: https://github.com/Yveradvir/Yvescmd
Author: YveRadvir
Classifier: Programming Language :: Python :: 3
Classifier: License :: OSI Approved :: MIT License
Classifier: Operating System :: OS Independent
